getpycode/__init__.py
getpycode/code_generator.py
getpycode/comment.py
getpycode/import_builder.py
getpycode/types.py
getpycode-0.2.0.dist-info/METADATA
getpycode-0.2.0.dist-info/WHEEL
getpycode-0.2.0.dist-info/licenses/LICENSE
getpycode-0.2.0.dist-info/RECORD
