Metadata-Version: 2.4
Name: getpycode
Version: 0.2.0
Summary: A Python code generator based on templates.
Project-URL: Homepage, https://github.com/Abstract-X/getpycode
Project-URL: Bug Tracker, https://github.com/Abstract-X/getpycode/issues
Author-email: Abstract-X <abstract-x-mail@protonmail.com>
License: MIT License
License-File: LICENSE
Classifier: License :: OSI Approved :: MIT License
Classifier: Operating System :: OS Independent
Classifier: Programming Language :: Python :: 3
Requires-Python: >=3.9
Requires-Dist: jinja2<4,>=3
